q/pipelines/__init__.py
q/pipelines/__init__.pyi
q/pipelines/specs.py
q/pipelines/types.py
q/pipelines/codegen/__init__.py
q/pipelines/codegen/__init__.pyi
q/pipelines/codegen/_local.py
q/pipelines/codegen/_pipelines.py
q/pipelines/codegen/_pipelines_init.py
q/pipelines/codegen/_types.py
q/pipelines/local/__init__.py
q/pipelines/local/__init__.pyi
q/pipelines/local/queues.py
q/pipelines/runners/__init__.py
q/pipelines/runners/__init__.pyi
q/pipelines/runners/_connect.py
q/pipelines/runners/_run.py
queue_pipelines-0.1.4.dist-info/METADATA
queue_pipelines-0.1.4.dist-info/WHEEL
queue_pipelines-0.1.4.dist-info/top_level.txt
queue_pipelines-0.1.4.dist-info/RECORD
