Metadata-Version: 2.1
Name: queue-pipelines
Version: 0.1.4
Summary: Declarative orchestration of asynchronous queue-based tasks
Author-email: Marcel Claramunt <marcel@moveread.com>
Project-URL: repo, https://github.com/marciclabas/pipelines.git
Requires-Python: >=3.10
Requires-Dist: queue-api
Requires-Dist: dslog
Requires-Dist: prettyprinter
Requires-Dist: fs-tools
Provides-Extra: all
Requires-Dist: queue-kv ; extra == 'all'
Requires-Dist: templang ; extra == 'all'
Provides-Extra: codegen
Requires-Dist: templang ; extra == 'codegen'
Provides-Extra: local
Requires-Dist: queue-kv ; extra == 'local'
